{
    "paths": [
        {
            "name": "/enqueue/{regionId}",
            "lambdaFunction": "enqueueRegionChange",
            "privacy": {
                "open": true
            },
            "policyResourceName": "/enqueue/*"
        }
    ],
    "resourceName": "enqueueRegionChange",
    "apiName": "enqueueRegionChange",
    "functionArns": [
        {
            "lambdaFunction": "enqueueRegionChange"
        }
    ],
    "privacy": {
        "auth": 0,
        "unauth": 0,
        "authRoleName": "amplify-kiyanaw-prod-214643-authRole",
        "unAuthRoleName": "amplify-kiyanaw-prod-214643-unauthRole"
    },
    "dependsOn": [
        {
            "category": "function",
            "resourceName": "enqueueRegionChange",
            "attributes": [
                "Name",
                "Arn"
            ]
        }
    ]
}